{
  "获取用例结果sql" : {
    "transaction" : "获取用例结果sql",
    "sampleCount" : 1,
    "errorCount" : 0,
    "errorPct" : 0.0,
    "meanResTime" : 1.0,
    "medianResTime" : 1.0,
    "minResTime" : 1.0,
    "maxResTime" : 1.0,
    "pct1ResTime" : 1.0,
    "pct2ResTime" : 1.0,
    "pct3ResTime" : 1.0,
    "throughput" : 1000.0,
    "receivedKBytesPerSec" : 369.140625,
    "sentKBytesPerSec" : 0.0
  },
  "获取casetype" : {
    "transaction" : "获取casetype",
    "sampleCount" : 1,
    "errorCount" : 0,
    "errorPct" : 0.0,
    "meanResTime" : 223.0,
    "medianResTime" : 223.0,
    "minResTime" : 223.0,
    "maxResTime" : 223.0,
    "pct1ResTime" : 223.0,
    "pct2ResTime" : 223.0,
    "pct3ResTime" : 223.0,
    "throughput" : 4.484304932735426,
    "receivedKBytesPerSec" : 0.0,
    "sentKBytesPerSec" : 0.0
  },
  "获取前置条件结果sql" : {
    "transaction" : "获取前置条件结果sql",
    "sampleCount" : 1,
    "errorCount" : 0,
    "errorPct" : 0.0,
    "meanResTime" : 4.0,
    "medianResTime" : 4.0,
    "minResTime" : 4.0,
    "maxResTime" : 4.0,
    "pct1ResTime" : 4.0,
    "pct2ResTime" : 4.0,
    "pct3ResTime" : 4.0,
    "throughput" : 250.0,
    "receivedKBytesPerSec" : 5.126953125,
    "sentKBytesPerSec" : 0.0
  },
  "获取条件状态" : {
    "transaction" : "获取条件状态",
    "sampleCount" : 1,
    "errorCount" : 0,
    "errorPct" : 0.0,
    "meanResTime" : 8.0,
    "medianResTime" : 8.0,
    "minResTime" : 8.0,
    "maxResTime" : 8.0,
    "pct1ResTime" : 8.0,
    "pct2ResTime" : 8.0,
    "pct3ResTime" : 8.0,
    "throughput" : 125.0,
    "receivedKBytesPerSec" : 1.0986328125,
    "sentKBytesPerSec" : 0.0
  },
  "获取用例sql" : {
    "transaction" : "获取用例sql",
    "sampleCount" : 1,
    "errorCount" : 0,
    "errorPct" : 0.0,
    "meanResTime" : 3116.0,
    "medianResTime" : 3116.0,
    "minResTime" : 3116.0,
    "maxResTime" : 3116.0,
    "pct1ResTime" : 3116.0,
    "pct2ResTime" : 3116.0,
    "pct3ResTime" : 3116.0,
    "throughput" : 0.32092426187419765,
    "receivedKBytesPerSec" : 0.118466182605905,
    "sentKBytesPerSec" : 0.0
  },
  "获取case-api的参数类型sql" : {
    "transaction" : "获取case-api的参数类型sql",
    "sampleCount" : 1,
    "errorCount" : 0,
    "errorPct" : 0.0,
    "meanResTime" : 4.0,
    "medianResTime" : 4.0,
    "minResTime" : 4.0,
    "maxResTime" : 4.0,
    "pct1ResTime" : 4.0,
    "pct2ResTime" : 4.0,
    "pct3ResTime" : 4.0,
    "throughput" : 250.0,
    "receivedKBytesPerSec" : 4.8828125,
    "sentKBytesPerSec" : 0.0
  },
  "获取计划结果sql" : {
    "transaction" : "获取计划结果sql",
    "sampleCount" : 1,
    "errorCount" : 0,
    "errorPct" : 0.0,
    "meanResTime" : 4.0,
    "medianResTime" : 4.0,
    "minResTime" : 4.0,
    "maxResTime" : 4.0,
    "pct1ResTime" : 4.0,
    "pct2ResTime" : 4.0,
    "pct3ResTime" : 4.0,
    "throughput" : 250.0,
    "receivedKBytesPerSec" : 47.8515625,
    "sentKBytesPerSec" : 0.0
  },
  "获取用例数据结果sql" : {
    "transaction" : "获取用例数据结果sql",
    "sampleCount" : 1,
    "errorCount" : 0,
    "errorPct" : 0.0,
    "meanResTime" : 2.0,
    "medianResTime" : 2.0,
    "minResTime" : 2.0,
    "maxResTime" : 2.0,
    "pct1ResTime" : 2.0,
    "pct2ResTime" : 2.0,
    "pct3ResTime" : 2.0,
    "throughput" : 500.0,
    "receivedKBytesPerSec" : 196.77734375,
    "sentKBytesPerSec" : 0.0
  },
  "获取run的参数" : {
    "transaction" : "获取run的参数",
    "sampleCount" : 1,
    "errorCount" : 0,
    "errorPct" : 0.0,
    "meanResTime" : 261.0,
    "medianResTime" : 261.0,
    "minResTime" : 261.0,
    "maxResTime" : 261.0,
    "pct1ResTime" : 261.0,
    "pct2ResTime" : 261.0,
    "pct3ResTime" : 261.0,
    "throughput" : 3.8314176245210727,
    "receivedKBytesPerSec" : 0.0,
    "sentKBytesPerSec" : 0.0
  },
  "获取发布单元结果sql" : {
    "transaction" : "获取发布单元结果sql",
    "sampleCount" : 1,
    "errorCount" : 0,
    "errorPct" : 0.0,
    "meanResTime" : 2.0,
    "medianResTime" : 2.0,
    "minResTime" : 2.0,
    "maxResTime" : 2.0,
    "pct1ResTime" : 2.0,
    "pct2ResTime" : 2.0,
    "pct3ResTime" : 2.0,
    "throughput" : 500.0,
    "receivedKBytesPerSec" : 12.20703125,
    "sentKBytesPerSec" : 0.0
  },
  "Total" : {
    "transaction" : "Total",
    "sampleCount" : 16,
    "errorCount" : 4,
    "errorPct" : 25.0,
    "meanResTime" : 342.81250000000006,
    "medianResTime" : 6.0,
    "minResTime" : 1.0,
    "maxResTime" : 3116.0,
    "pct1ResTime" : 1660.7000000000016,
    "pct2ResTime" : 3116.0,
    "pct3ResTime" : 3116.0,
    "throughput" : 1.7499726566772396,
    "receivedKBytesPerSec" : 0.17271153478070653,
    "sentKBytesPerSec" : 0.0
  },
  "获取被测服务器ip结果sql" : {
    "transaction" : "获取被测服务器ip结果sql",
    "sampleCount" : 1,
    "errorCount" : 0,
    "errorPct" : 0.0,
    "meanResTime" : 1.0,
    "medianResTime" : 1.0,
    "minResTime" : 1.0,
    "maxResTime" : 1.0,
    "pct1ResTime" : 1.0,
    "pct2ResTime" : 1.0,
    "pct3ResTime" : 1.0,
    "throughput" : 1000.0,
    "receivedKBytesPerSec" : 63.4765625,
    "sentKBytesPerSec" : 0.0
  },
  "获取api结果sql" : {
    "transaction" : "获取api结果sql",
    "sampleCount" : 1,
    "errorCount" : 0,
    "errorPct" : 0.0,
    "meanResTime" : 2.0,
    "medianResTime" : 2.0,
    "minResTime" : 2.0,
    "maxResTime" : 2.0,
    "pct1ResTime" : 2.0,
    "pct2ResTime" : 2.0,
    "pct3ResTime" : 2.0,
    "throughput" : 500.0,
    "receivedKBytesPerSec" : 59.5703125,
    "sentKBytesPerSec" : 0.0
  },
  "HttpApiPerformance" : {
    "transaction" : "HttpApiPerformance",
    "sampleCount" : 4,
    "errorCount" : 4,
    "errorPct" : 100.0,
    "meanResTime" : 464.25,
    "medianResTime" : 340.5,
    "minResTime" : 139.0,
    "maxResTime" : 1037.0,
    "pct1ResTime" : 1037.0,
    "pct2ResTime" : 1037.0,
    "pct3ResTime" : 1037.0,
    "throughput" : 3.3840947546531304,
    "receivedKBytesPerSec" : 0.0,
    "sentKBytesPerSec" : 0.0
  }
}