{
  "获取用例结果sql" : {
    "transaction" : "获取用例结果sql",
    "sampleCount" : 1,
    "errorCount" : 0,
    "errorPct" : 0.0,
    "meanResTime" : 2.0,
    "medianResTime" : 2.0,
    "minResTime" : 2.0,
    "maxResTime" : 2.0,
    "pct1ResTime" : 2.0,
    "pct2ResTime" : 2.0,
    "pct3ResTime" : 2.0,
    "throughput" : 500.0,
    "receivedKBytesPerSec" : 201.171875,
    "sentKBytesPerSec" : 0.0
  },
  "获取casetype" : {
    "transaction" : "获取casetype",
    "sampleCount" : 1,
    "errorCount" : 0,
    "errorPct" : 0.0,
    "meanResTime" : 41.0,
    "medianResTime" : 41.0,
    "minResTime" : 41.0,
    "maxResTime" : 41.0,
    "pct1ResTime" : 41.0,
    "pct2ResTime" : 41.0,
    "pct3ResTime" : 41.0,
    "throughput" : 24.390243902439025,
    "receivedKBytesPerSec" : 0.0,
    "sentKBytesPerSec" : 0.0
  },
  "获取前置条件结果sql" : {
    "transaction" : "获取前置条件结果sql",
    "sampleCount" : 1,
    "errorCount" : 0,
    "errorPct" : 0.0,
    "meanResTime" : 3.0,
    "medianResTime" : 3.0,
    "minResTime" : 3.0,
    "maxResTime" : 3.0,
    "pct1ResTime" : 3.0,
    "pct2ResTime" : 3.0,
    "pct3ResTime" : 3.0,
    "throughput" : 333.3333333333333,
    "receivedKBytesPerSec" : 6.8359375,
    "sentKBytesPerSec" : 0.0
  },
  "获取条件状态" : {
    "transaction" : "获取条件状态",
    "sampleCount" : 1,
    "errorCount" : 0,
    "errorPct" : 0.0,
    "meanResTime" : 8.0,
    "medianResTime" : 8.0,
    "minResTime" : 8.0,
    "maxResTime" : 8.0,
    "pct1ResTime" : 8.0,
    "pct2ResTime" : 8.0,
    "pct3ResTime" : 8.0,
    "throughput" : 125.0,
    "receivedKBytesPerSec" : 1.0986328125,
    "sentKBytesPerSec" : 0.0
  },
  "获取用例sql" : {
    "transaction" : "获取用例sql",
    "sampleCount" : 1,
    "errorCount" : 0,
    "errorPct" : 0.0,
    "meanResTime" : 976.0,
    "medianResTime" : 976.0,
    "minResTime" : 976.0,
    "maxResTime" : 976.0,
    "pct1ResTime" : 976.0,
    "pct2ResTime" : 976.0,
    "pct3ResTime" : 976.0,
    "throughput" : 1.0245901639344264,
    "receivedKBytesPerSec" : 0.4122374487704918,
    "sentKBytesPerSec" : 0.0
  },
  "获取case-api的参数类型sql" : {
    "transaction" : "获取case-api的参数类型sql",
    "sampleCount" : 1,
    "errorCount" : 0,
    "errorPct" : 0.0,
    "meanResTime" : 6.0,
    "medianResTime" : 6.0,
    "minResTime" : 6.0,
    "maxResTime" : 6.0,
    "pct1ResTime" : 6.0,
    "pct2ResTime" : 6.0,
    "pct3ResTime" : 6.0,
    "throughput" : 166.66666666666666,
    "receivedKBytesPerSec" : 3.2552083333333335,
    "sentKBytesPerSec" : 0.0
  },
  "获取计划结果sql" : {
    "transaction" : "获取计划结果sql",
    "sampleCount" : 1,
    "errorCount" : 0,
    "errorPct" : 0.0,
    "meanResTime" : 7.0,
    "medianResTime" : 7.0,
    "minResTime" : 7.0,
    "maxResTime" : 7.0,
    "pct1ResTime" : 7.0,
    "pct2ResTime" : 7.0,
    "pct3ResTime" : 7.0,
    "throughput" : 142.85714285714286,
    "receivedKBytesPerSec" : 27.34375,
    "sentKBytesPerSec" : 0.0
  },
  "获取用例数据结果sql" : {
    "transaction" : "获取用例数据结果sql",
    "sampleCount" : 1,
    "errorCount" : 0,
    "errorPct" : 0.0,
    "meanResTime" : 3.0,
    "medianResTime" : 3.0,
    "minResTime" : 3.0,
    "maxResTime" : 3.0,
    "pct1ResTime" : 3.0,
    "pct2ResTime" : 3.0,
    "pct3ResTime" : 3.0,
    "throughput" : 333.3333333333333,
    "receivedKBytesPerSec" : 133.13802083333334,
    "sentKBytesPerSec" : 0.0
  },
  "获取run的参数" : {
    "transaction" : "获取run的参数",
    "sampleCount" : 1,
    "errorCount" : 0,
    "errorPct" : 0.0,
    "meanResTime" : 263.0,
    "medianResTime" : 263.0,
    "minResTime" : 263.0,
    "maxResTime" : 263.0,
    "pct1ResTime" : 263.0,
    "pct2ResTime" : 263.0,
    "pct3ResTime" : 263.0,
    "throughput" : 3.802281368821293,
    "receivedKBytesPerSec" : 0.0,
    "sentKBytesPerSec" : 0.0
  },
  "获取发布单元结果sql" : {
    "transaction" : "获取发布单元结果sql",
    "sampleCount" : 1,
    "errorCount" : 0,
    "errorPct" : 0.0,
    "meanResTime" : 1.0,
    "medianResTime" : 1.0,
    "minResTime" : 1.0,
    "maxResTime" : 1.0,
    "pct1ResTime" : 1.0,
    "pct2ResTime" : 1.0,
    "pct3ResTime" : 1.0,
    "throughput" : 1000.0,
    "receivedKBytesPerSec" : 22.4609375,
    "sentKBytesPerSec" : 0.0
  },
  "Total" : {
    "transaction" : "Total",
    "sampleCount" : 21,
    "errorCount" : 9,
    "errorPct" : 42.857143,
    "meanResTime" : 509.57142857142867,
    "medianResTime" : 124.0,
    "minResTime" : 1.0,
    "maxResTime" : 3172.0,
    "pct1ResTime" : 2793.2000000000003,
    "pct2ResTime" : 3139.9999999999995,
    "pct3ResTime" : 3172.0,
    "throughput" : 2.774108322324967,
    "receivedKBytesPerSec" : 0.21788825132100395,
    "sentKBytesPerSec" : 0.0
  },
  "获取被测服务器ip结果sql" : {
    "transaction" : "获取被测服务器ip结果sql",
    "sampleCount" : 1,
    "errorCount" : 0,
    "errorPct" : 0.0,
    "meanResTime" : 1.0,
    "medianResTime" : 1.0,
    "minResTime" : 1.0,
    "maxResTime" : 1.0,
    "pct1ResTime" : 1.0,
    "pct2ResTime" : 1.0,
    "pct3ResTime" : 1.0,
    "throughput" : 1000.0,
    "receivedKBytesPerSec" : 63.4765625,
    "sentKBytesPerSec" : 0.0
  },
  "获取api结果sql" : {
    "transaction" : "获取api结果sql",
    "sampleCount" : 1,
    "errorCount" : 0,
    "errorPct" : 0.0,
    "meanResTime" : 2.0,
    "medianResTime" : 2.0,
    "minResTime" : 2.0,
    "maxResTime" : 2.0,
    "pct1ResTime" : 2.0,
    "pct2ResTime" : 2.0,
    "pct3ResTime" : 2.0,
    "throughput" : 500.0,
    "receivedKBytesPerSec" : 59.5703125,
    "sentKBytesPerSec" : 0.0
  },
  "HttpApiPerformance" : {
    "transaction" : "HttpApiPerformance",
    "sampleCount" : 9,
    "errorCount" : 9,
    "errorPct" : 100.0,
    "meanResTime" : 1043.111111111111,
    "medianResTime" : 146.0,
    "minResTime" : 124.0,
    "maxResTime" : 3172.0,
    "pct1ResTime" : 3172.0,
    "pct2ResTime" : 3172.0,
    "pct3ResTime" : 3172.0,
    "throughput" : 2.5641025641025643,
    "receivedKBytesPerSec" : 0.0,
    "sentKBytesPerSec" : 0.0
  }
}